deciphon_core/batch.py
deciphon_core/__init__.py
deciphon_core/interface.h
deciphon_core/sequence.py
deciphon_core/_cffi.o
deciphon_core/_cffi.c
deciphon_core/error.py
deciphon_core/scan.py
deciphon_core/press.py
deciphon_core/_cffi.pypy39-pp73-aarch64-linux-gnu.so
deciphon_core/include/imm_strlcpy.h
deciphon_core/include/imm_trellis.h
deciphon_core/include/h3r_result.h
deciphon_core/include/imm_matrixi16.h
deciphon_core/include/imm_range.h
deciphon_core/include/imm_trans.h
deciphon_core/include/imm_sym.h
deciphon_core/include/imm_table_state.h
deciphon_core/include/h3c_socket.h
deciphon_core/include/imm_state_vtable.h
deciphon_core/include/imm_fmt.h
deciphon_core/include/imm_path.h
deciphon_core/include/imm_codon_lprob.h
deciphon_core/include/imm_dp_cfg.h
deciphon_core/include/imm_state_table.h
deciphon_core/include/imm_nuclt_code.h
deciphon_core/include/imm_unreachable.h
deciphon_core/include/imm_amino.h
deciphon_core/include/deciphon.h
deciphon_core/include/imm_nuclt.h
deciphon_core/include/imm_ctrans.h
deciphon_core/include/imm_dna.h
deciphon_core/include/imm_tsort.h
deciphon_core/include/imm_max.h
deciphon_core/include/h3r_alidisplay.h
deciphon_core/include/imm_static_assert.h
deciphon_core/include/imm_frame_epsilon.h
deciphon_core/include/h3r_stats.h
deciphon_core/include/imm_ex3.h
deciphon_core/include/imm_str.h
deciphon_core/include/imm_ex1.h
deciphon_core/include/lite_pack.h
deciphon_core/include/imm_ipow.h
deciphon_core/include/imm_stack.h
deciphon_core/include/imm_min.h
deciphon_core/include/imm_compiler.h
deciphon_core/include/lio.h
deciphon_core/include/h3c_clock.h
deciphon_core/include/imm_mute_state.h
deciphon_core/include/imm_gencode.h
deciphon_core/include/imm_score_table.h
deciphon_core/include/imm_array_size_field.h
deciphon_core/include/imm_rc.h
deciphon_core/include/imm_prod.h
deciphon_core/include/imm_unroll.h
deciphon_core/include/imm_emis.h
deciphon_core/include/imm_normal_state.h
deciphon_core-1.0.16.dist-info/LICENSE
deciphon_core-1.0.16.dist-info/WHEEL
deciphon_core-1.0.16.dist-info/METADATA
deciphon_core-1.0.16.dist-info/RECORD
